MANIFEST.in
README.rst
setup.py
test.py
docs/CREDITS.txt
docs/HISTORY.rst
docs/LICENSE.txt
src/roughrider/__init__.py
src/roughrider.token.egg-info/PKG-INFO
src/roughrider.token.egg-info/SOURCES.txt
src/roughrider.token.egg-info/dependency_links.txt
src/roughrider.token.egg-info/namespace_packages.txt
src/roughrider.token.egg-info/not-zip-safe
src/roughrider.token.egg-info/requires.txt
src/roughrider.token.egg-info/top_level.txt
src/roughrider/token/__init__.py
src/roughrider/token/errors.py
src/roughrider/token/hmac_factories.py
src/roughrider/token/meta.py
src/roughrider/token/secret.py
tests/test_hmac_token.py